P2HNNS
