Metadata-Version: 2.1
Name: P2HNNS
Version: 1.0.2
Summary: A Python library for efficient Point-to-hyperplane nearest neighbours search (P2HNNS)
Home-page: https://github.com/petrosDemetrakopoulos/P2HNNS
Download-URL: https://github.com/petrosDemetrakopoulos/P2HNNS/archive/refs/tags/1.0.0.tar.gz
Author: Petros Demetrakopoulos
Author-email: petrosdem@gmail.com
License: MIT
Keywords: KNN,similarity,search,hyperplance,point,nearest,neighbours
Classifier: Development Status :: 5 - Production/Stable
Classifier: Intended Audience :: Developers
Classifier: Topic :: Software Development :: Build Tools
Classifier: License :: OSI Approved :: MIT License
Classifier: Programming Language :: Python :: 3
Classifier: Programming Language :: Python :: 3.4
Classifier: Programming Language :: Python :: 3.5
Classifier: Programming Language :: Python :: 3.6
License-File: LICENSE
